MagicConvert/MagicConvert.py
MagicConvert/__init__.py
magicconvert-0.1.3.dist-info/licenses/LICENSE
magicconvert-0.1.3.dist-info/METADATA
magicconvert-0.1.3.dist-info/WHEEL
magicconvert-0.1.3.dist-info/top_level.txt
magicconvert-0.1.3.dist-info/RECORD
