Metadata-Version: 2.4
Name: MagicConvert
Version: 0.1.3
Summary: MagicConvert is a Python library that converts various document formats (PDF, DOCX, XLSX, PPTX, HTML, Images) to markdown text. Features include OCR support, automatic format detection, and URL/file stream handling.
Author-email: Muhammad Noman <muhammadnomanshafiq76@gmail.com>
Maintainer-email: Muhammad Noman <muhammadnomanshafiq76@gmail.com>
License-Expression: MIT
Project-URL: Homepage, https://github.com/MuhammadNoman76/MagicConvert
Project-URL: Repository, https://github.com/MuhammadNoman76/MagicConvert
Project-URL: Issue Tracker, https://github.com/MuhammadNoman76/MagicConvert/issues
Project-URL: LinkedIn, https://www.linkedin.com/in/muhammad-noman76
Keywords: document-conversion,markdown,ocr,pdf-to-markdown,docx-to-markdown,xlsx-to-markdown,pptx-to-markdown,html-to-markdown,image-to-text,python-library,text-extraction,document-processing,format-detection,tesseract-ocr,file-conversion,text-processing
Classifier: Development Status :: 5 - Production/Stable
Classifier: Intended Audience :: Developers
Classifier: Intended Audience :: Science/Research
Classifier: Programming Language :: Python :: 3
Classifier: Programming Language :: Python :: 3.8
Classifier: Programming Language :: Python :: 3.9
Classifier: Programming Language :: Python :: 3.10
Classifier: Programming Language :: Python :: 3.11
Classifier: Programming Language :: Python :: 3.12
Classifier: Topic :: Scientific/Engineering :: Artificial Intelligence
Classifier: Topic :: Text Processing :: General
Classifier: Topic :: Office/Business
Classifier: Topic :: Software Development :: Libraries :: Python Modules
Requires-Python: >=3.8
License-File: LICENSE
Requires-Dist: mammoth>=1.4.0
Requires-Dist: markdownify>=0.11.0
Requires-Dist: pandas>=1.0.0
Requires-Dist: pdfminer.six>=20200517
Requires-Dist: python-pptx>=0.6.18
Requires-Dist: puremagic>=1.11
Requires-Dist: requests>=2.25.0
Requires-Dist: beautifulsoup4>=4.9.0
Requires-Dist: charset-normalizer>=2.0.0
Requires-Dist: Pillow>=8.0.0
Requires-Dist: pytesseract>=0.3.0
Requires-Dist: openpyxl>=3.0.0
Provides-Extra: dev
Requires-Dist: pytest>=6.0; extra == "dev"
Requires-Dist: pytest-cov>=2.0; extra == "dev"
Requires-Dist: black>=21.0; extra == "dev"
Requires-Dist: isort>=5.0; extra == "dev"
Requires-Dist: flake8>=3.8; extra == "dev"
Dynamic: license-file
